hes_off/__init__.py
hes_off/__pycache__/__init__.cpython-38.pyc
hes_off/app/__init__.py
hes_off/app/forms.py
hes_off/app/routes.py
hes_off/app/utilities.py
hes_off/app/__pycache__/__init__.cpython-38.pyc
hes_off/app/__pycache__/forms.cpython-38.pyc
hes_off/app/__pycache__/routes.cpython-38.pyc
hes_off/app/__pycache__/utilities.cpython-38.pyc
hes_off/app/static/logo_dark.svg
hes_off/app/static/logo_light.svg
hes_off/app/static/style.css
hes_off/app/templates/about.html
hes_off/app/templates/base.html
hes_off/app/templates/docs.html
hes_off/app/templates/gui.html
hes_off/app/uploads/edward_grieg.cfg
hes_off/core/__init__.py
hes_off/core/integrated_model.py
hes_off/core/process_model.py
hes_off/core/utilities.py
hes_off/core/__pycache__/__init__.cpython-38.pyc
hes_off/core/__pycache__/integrated_model.cpython-38.pyc
hes_off/core/__pycache__/process_model.compute_EL_efficiency-288.py38.1.nbc
hes_off/core/__pycache__/process_model.compute_EL_efficiency-288.py38.nbi
hes_off/core/__pycache__/process_model.compute_EL_hydrogen_production-328.py38.1.nbc
hes_off/core/__pycache__/process_model.compute_EL_hydrogen_production-328.py38.nbi
hes_off/core/__pycache__/process_model.compute_FC_efficiency-339.py38.1.nbc
hes_off/core/__pycache__/process_model.compute_FC_efficiency-339.py38.nbi
hes_off/core/__pycache__/process_model.compute_FC_hydrogen_consumption-378.py38.1.nbc
hes_off/core/__pycache__/process_model.compute_FC_hydrogen_consumption-378.py38.nbi
hes_off/core/__pycache__/process_model.compute_GT_carbon_dioxide_emissions-531.py38.1.nbc
hes_off/core/__pycache__/process_model.compute_GT_carbon_dioxide_emissions-531.py38.nbi
hes_off/core/__pycache__/process_model.compute_GT_efficiency-445.py38.1.nbc
hes_off/core/__pycache__/process_model.compute_GT_efficiency-445.py38.nbi
hes_off/core/__pycache__/process_model.compute_GT_fuel_consumption-524.py38.1.nbc
hes_off/core/__pycache__/process_model.compute_GT_fuel_consumption-524.py38.nbi
hes_off-1.0.1.dist-info/LICENSE.md
hes_off-1.0.1.dist-info/METADATA
hes_off-1.0.1.dist-info/WHEEL
hes_off-1.0.1.dist-info/top_level.txt
hes_off-1.0.1.dist-info/RECORD
