Metadata-Version: 2.1
Name: hes-off
Version: 1.0.1
Summary: A package for the simulation of hybrid energy systems for off-shore oil and gas installations.
Home-page: https://github.com/RoberAgro/HES-OFF
Author: Roberto Agromayor
Author-email: rober.agro@gmail.com
License: UNKNOWN
Platform: UNKNOWN
Classifier: Programming Language :: Python :: 3
Classifier: License :: OSI Approved :: MIT License
Requires-Python: >=3
Requires-Dist: certifi (==2020.12.5)
Requires-Dist: click (==7.1.2)
Requires-Dist: cycler (==0.10.0)
Requires-Dist: Flask (==1.1.2)
Requires-Dist: Flask-WTF (==0.14.3)
Requires-Dist: gunicorn (==20.1.0)
Requires-Dist: importlib-resources (==5.1.2)
Requires-Dist: itsdangerous (==1.1.0)
Requires-Dist: Jinja2 (==2.11.3)
Requires-Dist: kiwisolver (==1.3.1)
Requires-Dist: llvmlite (==0.36.0)
Requires-Dist: MarkupSafe (==1.1.1)
Requires-Dist: matplotlib (==3.4.1)
Requires-Dist: numba (==0.53.1)
Requires-Dist: numpy (==1.20.2)
Requires-Dist: Pillow (==8.2.0)
Requires-Dist: pip (==21.1.1)
Requires-Dist: pyparsing (==2.4.7)
Requires-Dist: python-dateutil (==2.8.1)
Requires-Dist: PyYAML (==5.4.1)
Requires-Dist: scipy (==1.6.3)
Requires-Dist: six (==1.15.0)
Requires-Dist: Werkzeug (==1.0.1)
Requires-Dist: wheel (==0.36.2)
Requires-Dist: wincertstore (==0.2)
Requires-Dist: WTForms (==2.3.3)
